luatable/__init__.py
luatable/table.py
luatables-1.0.1.1.dist-info/LICENCE
luatables-1.0.1.1.dist-info/METADATA
luatables-1.0.1.1.dist-info/WHEEL
luatables-1.0.1.1.dist-info/top_level.txt
luatables-1.0.1.1.dist-info/RECORD
