Metadata-Version: 2.1
Name: luatables
Version: 1.0.1.1
Summary: Lua tables in Python
Home-page: https://github.com/SkyTheCodeMaster/python-lua-tables
Author: Sky The Code Master
Author-email: sky@skystuff.games
License: UNKNOWN
Project-URL: Bug Tracker, https://github.com/SkyTheCodeMaster/python-lua-tables/issues
Platform: UNKNOWN
Classifier: Programming Language :: Python :: 3
Classifier: License :: OSI Approved :: MIT License
Classifier: Operating System :: OS Independent
Requires-Python: >=3.6
License-File: LICENCE
